pyVisio/__init__.py
pyVisio/analysis.py
pyVisio/charts.py
pyVisio/data_analysis.py
pyVisio/data_cleaning.py
pyVisio/data_utils.py
pyVisio/live_charts.py
pyVisio/regression.py
pyVisio/reporting.py
pyVisio/themes.py
pyVisio/utils.py
tests/__init__.py
tests/test_bar_chart.py
tests/test_charts.py
tests/test_line_chart.py
tests/test_pie_chart.py
tests/test_pyVisio.py
tests/test_scatter_plot.py
pyVisio-1.7.dist-info/LICENSE
pyVisio-1.7.dist-info/METADATA
pyVisio-1.7.dist-info/WHEEL
pyVisio-1.7.dist-info/top_level.txt
pyVisio-1.7.dist-info/RECORD
