Metadata-Version: 2.1
Name: pyVisio
Version: 1.7
Summary: Interactive and dynamic data visualization library
Home-page: https://github.com/kayahuseyinn/pyVisio
Author: Hüseyin Kaya
Author-email: kaya87826@gmail.com
Classifier: Programming Language :: Python :: 3
Classifier: License :: OSI Approved :: MIT License
Classifier: Operating System :: OS Independent
Requires-Python: >=3.6
License-File: LICENSE
Requires-Dist: matplotlib
Requires-Dist: plotly
Requires-Dist: pandas
Requires-Dist: numpy
Requires-Dist: statsmodels
Requires-Dist: jinja2
Requires-Dist: reportlab
